isolator/__init__.py
isolator/isolator.py
isolator-0.1.1.dist-info/LICENSE
isolator-0.1.1.dist-info/METADATA
isolator-0.1.1.dist-info/WHEEL
isolator-0.1.1.dist-info/top_level.txt
isolator-0.1.1.dist-info/RECORD
