Metadata-Version: 2.1
Name: isolator
Version: 0.1.1
Summary: Isolate a python class into a separate process
Home-page: https://github.com/neuneck/isolator
License: mit
Platform: UNKNOWN
Classifier: Development Status :: 3 - Alpha
Classifier: Programming Language :: Python :: 3
Classifier: License :: OSI Approved :: MIT License
Classifier: Operating System :: Unix
Requires-Python: >=3.6
